project/huffman/verilog/huffman_w.v
module huffman_w (clk, reset, in, valid_in, out, valid);

parameter num_words = 8; //determined by the 8 by 8 MAC array
parameter bw = 4; //number of bits per word, which is fixed

input clk;
input reset; //assumes posedge reset
input in;
input valid_in; //allows for pausing, else just set to true
output wire [bw*num_words-1: 0] out;
output valid;
// Define states, leaf node states are encoded with their preencoded data

localparam S_ERROR = 5'd31;
localparam S_ROOT =  5'd25;
localparam S0 =  5'd27;
localparam S00 =  5'd29;
localparam S000 =  5'd22;
localparam S0000 =  5'd16;
localparam S00000 =  5'd5; //leaf
localparam S00001 =  5'd12; //leaf
localparam S0001 =  5'd4; //leaf
localparam S001 =  5'd18; 
localparam S0010 =  5'd13; //leaf
localparam S0011 =  5'd21; 
localparam S00110 =  5'd30;
localparam S00111 =  5'd14; //leaf
localparam S001101 =  5'd23;
localparam S0011010 =  5'd9; //leaf
localparam S001100 =  5'd6; //leaf
localparam S0011011 =  5'd17;
localparam S00110110 =  5'd10; //leaf
localparam S00110111 =  5'd19; 
localparam S001101110 =  5'd20; 
localparam S001101111 =  5'd11; //leaf
localparam S0011011100 =  5'd8; //leaf
localparam S0011011101 =  5'd15; //leaf
localparam S01 =  5'd24; 
localparam S010 =  5'd1; //leaf
localparam S011 =  5'd26; 
localparam S0110 =  5'd2; //leaf
localparam S0111 =  5'd28;
localparam S01110 =  5'd3; //leaf
localparam S01111 =  5'd7; //leaf
localparam S1 =  5'd0; //leaf


// Current state register
reg [4:0] state; //5 bits to represent 31 states
reg [4:0] next_state; //5 bits to represent 31 states, should act as a wire

reg [bw*num_words-1: 0] buffered_outputs; //store words until full then send valid
reg valid_reg; //so we can delay valid single by 1 cycle
reg isLeaf; //if next state is leaf, should act as wire
reg [2:0] buffer_ptr;  //curr slot we write to in buffer

assign valid = valid_reg;
assign out = buffered_outputs;

// Always FF
always @(posedge clk) begin
    if (reset) begin
        state <= S_ROOT;
        buffered_outputs <= 32'b00000000000000000000000000000000;
        buffer_ptr <= 3'b111;
    end
    else begin
        state <= next_state;
        valid_reg <= (isLeaf & (buffer_ptr == 3'b000)); //if writing to last element
        if (isLeaf) begin
            buffered_outputs[(buffer_ptr + 1)*bw - 1 -: bw] <= next_state; 
            if (buffer_ptr == 3'b000) begin
                buffer_ptr <= 3'b111;
            end else
                buffer_ptr <= buffer_ptr - 1;
        end
        
    end
end

// Comb logic
always @(*) begin
    if (reset) begin
        next_state = S_ROOT;
        isLeaf = 1'b0; 
    end
    else if (!valid_in) begin
        next_state = state;
        isLeaf = 1'b0; 
    end
    else 
        case (state)
            S_ROOT:
            begin
                if (in == 1'b1) begin
                    isLeaf = 1'b1;
                    next_state = S1;
                end else begin
                    isLeaf = 1'b0;
                    next_state = S0;
                end
            end
            S0:
            begin
                isLeaf = 1'b0;
                if (in == 1'b1) 
                    next_state = S01;
                else
                    next_state = S00;                
            end
            S00:
            begin
                isLeaf = 1'b0;
                if (in == 1'b1) 
                    next_state = S001;
                else
                    next_state = S000;  
            end
            S000:
            begin
                if (in == 1'b1) begin
                    isLeaf = 1'b1;
                    next_state = S0001;
                end else begin
                    isLeaf = 1'b0;
                    next_state = S0000;  
                end
            end
            S0000:
            begin
                isLeaf = 1'b1;
                if (in == 1'b1)
                    next_state = S00001;
                else
                    next_state = S00000;  
            end
            S00000: //leaf
            begin
                if (in == 1'b1) begin
                    next_state = S1;
                    isLeaf = 1'b1;
                end else begin
                    next_state = S0;  
                    isLeaf = 1'b0;
                end
            end
            S00001: //leaf
            begin
                if (in == 1'b1) begin
                    next_state = S1;
                    isLeaf = 1'b1;
                end else begin
                    next_state = S0;  
                    isLeaf = 1'b0;
                end
            end
            S0001: //leaf
            begin
                if (in == 1'b1) begin
                    next_state = S1;
                    isLeaf = 1'b1;
                end else begin
                    next_state = S0;  
                    isLeaf = 1'b0;
                end
            end
            S001:
            begin
                if (in == 1'b1) begin
                    isLeaf = 1'b0;
                    next_state = S0011;
                end else begin
                    isLeaf = 1'b1;
                    next_state = S0010; 
                end
            end
            S0010: //leaf
            begin
                if (in == 1'b1) begin
                    next_state = S1;
                    isLeaf = 1'b1;
                end else begin
                    next_state = S0;  
                    isLeaf = 1'b0;
                end
            end
            S0011:
            begin
                if (in == 1'b1) begin
                    isLeaf = 1'b1;
                    next_state = S00111;
                end else begin
                    isLeaf = 1'b0;
                    next_state = S00110;
                end  
            end
            S00110:
            begin
                if (in == 1'b1) begin
                    isLeaf = 1'b0;
                    next_state = S001101;
                end else begin
                    isLeaf = 1'b1;
                    next_state = S001100;
                end  
            end
            S00111: //leaf
            begin
               if (in == 1'b1) begin
                    next_state = S1;
                    isLeaf = 1'b1;
                end else begin
                    next_state = S0;  
                    isLeaf = 1'b0;
                end  
            end
            S001101:
            begin
                if (in == 1'b1) begin
                    isLeaf = 1'b0;
                    next_state = S0011011;
                end else begin
                    isLeaf = 1'b1;
                    next_state = S0011010;  
                end
            end
            S0011010: //leaf
            begin
                if (in == 1'b1) begin
                    next_state = S1;
                    isLeaf = 1'b1;
                end else begin
                    next_state = S0;  
                    isLeaf = 1'b0;
                end
            end
            S001100: //leaf
            begin
               if (in == 1'b1) begin
                    next_state = S1;
                    isLeaf = 1'b1;
                end else begin
                    next_state = S0;  
                    isLeaf = 1'b0;
                end
            end
            S0011011:
            begin
                if (in == 1'b1) begin
                    isLeaf = 1'b0;
                    next_state = S00110111;
                end else begin
                    isLeaf = 1'b1;
                    next_state = S00110110;  
                end
            end
            S00110110: //leaf
            begin
                if (in == 1'b1) begin
                    next_state = S1;
                    isLeaf = 1'b1;
                end else begin
                    next_state = S0;  
                    isLeaf = 1'b0;
                end
            end
            S00110111:
            begin
                if (in == 1'b1) begin 
                    isLeaf = 1'b1;
                    next_state = S001101111;
                end else begin
                    isLeaf = 1'b0;
                    next_state = S001101110;
                end
            end
            S001101110:
            begin
                if (in == 1'b1) begin
                    next_state = S0011011101;
                    isLeaf = 1'b1;
                end else begin
                    next_state = S0011011100;
                    isLeaf = 1'b1;
                end
            end 
            S001101111: //leaf
            begin
                if (in == 1'b1) begin
                    next_state = S1;
                    isLeaf = 1'b1;
                end else begin
                    next_state = S0;  
                    isLeaf = 1'b0;
                end
            end
            S0011011100: //leaf 
            begin
                if (in == 1'b1) begin
                    next_state = S1;
                    isLeaf = 1'b1;
                end else begin
                    next_state = S0;  
                    isLeaf = 1'b0;
                end
            end
            S0011011101: //leaf
            begin
                if (in == 1'b1) begin
                    next_state = S1;
                    isLeaf = 1'b1;
                end else begin
                    next_state = S0;  
                    isLeaf = 1'b0;
                end
            end
            S01:
            begin
                if (in == 1'b1) begin
                    isLeaf = 1'b0;
                    next_state = S011;
                end else begin
                    isLeaf = 1'b1;
                    next_state = S010; 
                end
            end
            S010: //leaf
            begin
               if (in == 1'b1) begin
                    next_state = S1;
                    isLeaf = 1'b1;
                end else begin
                    next_state = S0;  
                    isLeaf = 1'b0;
                end
            end
            S011:
            begin
                if (in == 1'b1) begin 
                    isLeaf = 1'b0;
                    next_state = S0111;    
                end else begin
                    isLeaf = 1'b1;
                    next_state = S0110;
                end  
            end
            S0110: //leaf
            begin
                if (in == 1'b1) begin
                    next_state = S1;
                    isLeaf = 1'b1;
                end else begin
                    next_state = S0;  
                    isLeaf = 1'b0;
                end
            end
            S0111:
            begin
                isLeaf = 1'b1;
                if (in == 1'b1) 
                    next_state = S01111;
                else
                    next_state = S01110;  
            end
            S01110: //leaf
            begin
                if (in == 1'b1) begin
                    next_state = S1;
                    isLeaf = 1'b1;
                end else begin
                    next_state = S0;  
                    isLeaf = 1'b0;
                end
            end
            S01111: //leaf
            begin
               if (in == 1'b1) begin
                    next_state = S1;
                    isLeaf = 1'b1;
                end else begin
                    next_state = S0;  
                    isLeaf = 1'b0;
                end
            end
            S1: //leaf
            begin
               if (in == 1'b1) begin
                    next_state = S1;
                    isLeaf = 1'b1;
                end else begin
                    next_state = S0;  
                    isLeaf = 1'b0;
                end
            end
            default: begin
                isLeaf = 1'b0;
                next_state = S_ERROR; //illegal transistion not in tree 
            end
        endcase
end
endmodule

project/huffman/verilog/huffman_w_tb.v
module huffman_w_tb;

parameter num_words = 8; //determined by the 8 by 8 MAC array
parameter bw = 4; //number of bits per word, which is fixed

reg clk = 0;
reg reset = 0;
reg in;
reg valid_in = 1'b1;
wire [bw*num_words-1: 0] out;
wire valid;

integer counter = 0;
integer curr_cycles = 2;
integer w_file ; // file handler
integer w_scan_file ; // file handler

integer captured_data;

huffman_w huff_instance (
        .clk(clk),
        .reset(reset), 
        .valid_in(valid_in),
        .in(in), 
        .out(out),
        .valid(valid));

initial begin 

  w_file = $fopen("encoded_weights.txt", "r");  //weight data

  $dumpfile("huffman_w_tb.vcd");
  $dumpvars(0,huffman_w_tb);
 

  #1 clk = 1'b0;  reset = 1;
  #1 clk = 1'b1;  
  #1 clk = 1'b0;  
  #1 clk = 1'b1; reset = 0;  
  $display("-------------------- Computation start --------------------");
  
  while (!$feof(w_file)) begin

    w_scan_file = $fscanf(w_file, "%c\n", captured_data);
    //if (captured_data == "1")
      //$display("%c", captured_data);
    //else
    if (captured_data == "1")
      in = 1'b1;
    else
      in = 1'b0;
    if (valid) begin
      $display("%b", out);
      counter = counter + 1;
      //if (counter % 8 == 0)
        //$display("\n");
    end

    //$display("%c", captured_data);
      #1 clk = 1'b0;
      #1 clk = 1'b1;
      curr_cycles = curr_cycles + 2;
  end

  #1 clk = 1'b0;
  #1 clk = 1'b1;
  if (valid) begin
      $display("%b", out);
      counter = counter + 1;
      //if (counter % 8 == 0)
        //$display("\n");
    end

  #10 $finish;


end

endmodule

project/huffman/huffman_w_tb.vcd
$date
	Wed Dec 06 01:50:45 2023
$end
$version
	Icarus Verilog
$end
$timescale
	1s
$end
$scope module huffman_w_tb $end
$var wire 1 ! valid $end
$var wire 32 " out [31:0] $end
$var parameter 32 # bw $end
$var parameter 32 $ num_words $end
$var reg 1 % clk $end
$var reg 1 & in $end
$var reg 1 ' reset $end
$var reg 1 ( valid_in $end
$var integer 32 ) captured_data [31:0] $end
$var integer 32 * counter [31:0] $end
$var integer 32 + curr_cycles [31:0] $end
$var integer 32 , w_file [31:0] $end
$var integer 32 - w_scan_file [31:0] $end
$scope module huff_instance $end
$var wire 1 % clk $end
$var wire 1 & in $end
$var wire 32 . out [31:0] $end
$var wire 1 ' reset $end
$var wire 1 ! valid $end
$var wire 1 ( valid_in $end
$var parameter 5 / S0 $end
$var parameter 5 0 S00 $end
$var parameter 5 1 S000 $end
$var parameter 5 2 S0000 $end
$var parameter 5 3 S00000 $end
$var parameter 5 4 S00001 $end
$var parameter 5 5 S0001 $end
$var parameter 5 6 S001 $end
$var parameter 5 7 S0010 $end
$var parameter 5 8 S0011 $end
$var parameter 5 9 S00110 $end
$var parameter 5 : S001100 $end
$var parameter 5 ; S001101 $end
$var parameter 5 < S0011010 $end
$var parameter 5 = S0011011 $end
$var parameter 5 > S00110110 $end
$var parameter 5 ? S00110111 $end
$var parameter 5 @ S001101110 $end
$var parameter 5 A S0011011100 $end
$var parameter 5 B S0011011101 $end
$var parameter 5 C S001101111 $end
$var parameter 5 D S00111 $end
$var parameter 5 E S01 $end
$var parameter 5 F S010 $end
$var parameter 5 G S011 $end
$var parameter 5 H S0110 $end
$var parameter 5 I S0111 $end
$var parameter 5 J S01110 $end
$var parameter 5 K S01111 $end
$var parameter 5 L S1 $end
$var parameter 5 M S_ERROR $end
$var parameter 5 N S_ROOT $end
$var parameter 32 O bw $end
$var parameter 32 P num_words $end
$var reg 3 Q buffer_ptr [2:0] $end
$var reg 32 R buffered_outputs [31:0] $end
$var reg 1 S isLeaf $end
$var reg 5 T next_state [4:0] $end
$var reg 5 U state [4:0] $end
$var reg 1 V valid_reg $end
$upscope $end
$upscope $end
$enddefinitions $end
$comment Show the parameter values. $end
$dumpall
b1000 P
b100 O
b11001 N
b11111 M
b0 L
b111 K
b11 J
b11100 I
b10 H
b11010 G
b1 F
b11000 E
b1110 D
b1011 C
b1111 B
b1000 A
b10100 @
b10011 ?
b1010 >
b10001 =
b1001 <
b10111 ;
b110 :
b11110 9
b10101 8
b1101 7
b10010 6
b100 5
b1100 4
b101 3
b10000 2
b10110 1
b11101 0
b11011 /
b1000 $
b100 #
$end
#0
$dumpvars
xV
bx U
b11111 T
0S
bx R
bx Q
bx .
bx -
b10000000000000000000000000000011 ,
b10 +
b0 *
bx )
1(
0'
x&
0%
bx "
x!
$end
#1
b11001 T
1'
#2
b111 Q
b0 "
b0 .
b0 R
b11001 U
1%
#3
0%
#4
0!
0V
b0 T
1S
1&
b1 -
b110001 )
0'
1%
#5
0%
#6
b110 Q
b0 U
b100 +
1%
#7
0%
#8
b101 Q
b110 +
1%
#9
0%
#10
b100 Q
b1000 +
1%
#11
0%
#12
b11 Q
0S
b11011 T
0&
b110000 )
b1010 +
1%
#13
0%
#14
b11011 U
0S
b11000 T
1&
b110001 )
b1100 +
1%
#15
0%
#16
1S
b11000 U
b1 T
0&
b110000 )
b1110 +
1%
#17
0%
#18
b10 Q
b1000000000000 "
b1000000000000 .
b1000000000000 R
b1 U
b0 T
1S
1&
b110001 )
b10000 +
1%
#19
0%
#20
b1 Q
b0 U
b10010 +
1%
#21
0%
#22
b0 Q
b10100 +
1%
#23
0%
#24
b111 Q
1!
1V
b10110 +
1%
#25
0%
#26
b110 Q
0!
0V
b1 *
b11000 +
1%
#27
0%
#28
b101 Q
b11010 +
1%
#29
0%
#30
b100 Q
b11100 +
1%
#31
0%
#32
b11 Q
b11110 +
1%
#33
0%
#34
b10 Q
b0 "
b0 .
b0 R
b100000 +
1%
#35
0%
#36
b1 Q
b100010 +
1%
#37
0%
#38
b0 Q
b100100 +
1%
#39
0%
#40
b111 Q
1!
1V
b100110 +
1%
#41
0%
#42
b110 Q
0!
0V
b10 *
b101000 +
1%
#43
0%
#44
b101 Q
b101010 +
1%
#45
0%
#46
b100 Q
b101100 +
1%
#47
0%
#48
b11 Q
b101110 +
1%
#49
0%
#50
b10 Q
b110000 +
1%
#51
0%
#52
b1 Q
b110010 +
1%
#53
0%
#54
b0 Q
b110100 +
1%
#55
0%
#56
b111 Q
1!
1V
b110110 +
1%
#57
0%
#58
b110 Q
0!
0V
b11 *
b111000 +
1%
#59
0%
#60
b101 Q
b111010 +
1%
#61
0%
#62
b100 Q
b111100 +
1%
#63
0%
#64
b11 Q
b111110 +
1%
#65
0%
#66
b10 Q
b1000000 +
1%
#67
0%
#68
b1 Q
b1000010 +
1%
#69
0%
#70
b0 Q
b1000100 +
1%
#71
0%
#72
b111 Q
1!
1V
b1000110 +
1%
#73
0%
#74
b110 Q
0!
0V
b100 *
b1001000 +
1%
#75
0%
#76
b101 Q
b1001010 +
1%
#77
0%
#78
b100 Q
b1001100 +
1%
#79
0%
#80
b11 Q
b1001110 +
1%
#81
0%
#82
b10 Q
b1010000 +
1%
#83
0%
#84
b1 Q
b1010010 +
1%
#85
0%
#86
b0 Q
b1010100 +
1%
#87
0%
#88
b111 Q
1!
1V
b1010110 +
1%
#89
0%
#90
b110 Q
0!
0V
b101 *
b1011000 +
1%
#91
0%
#92
b101 Q
b1011010 +
1%
#93
0%
#94
b100 Q
b1011100 +
1%
#95
0%
#96
b11 Q
b1011110 +
1%
#97
0%
#98
b10 Q
b1100000 +
1%
#99
0%
#100
b1 Q
b1100010 +
1%
#101
0%
#102
b0 Q
b1100100 +
1%
#103
0%
#104
b111 Q
1!
1V
b1100110 +
1%
#105
0%
#106
b110 Q
0!
0V
b110 *
b1101000 +
1%
#107
0%
#108
b101 Q
b1101010 +
1%
#109
0%
#110
b100 Q
b1101100 +
1%
#111
0%
#112
b11 Q
0S
b11011 T
0&
b110000 )
b1101110 +
1%
#113
0%
#114
b11011 U
0S
b11000 T
1&
b110001 )
b1110000 +
1%
#115
0%
#116
1S
b11000 U
b1 T
0&
b110000 )
b1110010 +
1%
#117
0%
#118
b10 Q
b1000000000000 "
b1000000000000 .
b1000000000000 R
b1 U
b0 T
1S
1&
b110001 )
b1110100 +
1%
#119
0%
#120
b1 Q
b0 U
b1110110 +
1%
#121
0%
#122
b0 Q
b1111000 +
1%
#123
0%
#124
b111 Q
1!
1V
b1111010 +
1%
#125
0%
#126
b110 Q
0!
0V
b111 *
b1111100 +
1%
#127
0%
#128
b101 Q
b1111110 +
1%
#129
0%
#130
b100 Q
b10000000 +
1%
#131
0%
#132
b11 Q
b10000010 +
1%
#133
0%
#134
b10 Q
b0 "
b0 .
b0 R
b10000100 +
1%
#135
0%
#136
b1 Q
b10000110 +
1%
#137
0%
#138
b0 Q
b10001000 +
1%
#139
0%
#140
b111 Q
1!
1V
0S
b11011 T
0&
b110000 )
b10001010 +
1%
#141
0%
#142
b11101 T
0!
0V
b11011 U
b1000 *
b10001100 +
1%
#143
0%
#144
b10110 T
b11101 U
b10001110 +
1%
#145
0%
#146
b10000 T
b10110 U
b10010000 +
1%
#147
0%
#148
b10000 U
b1100 T
1S
1&
b110001 )
b10010010 +
1%
#149
0%
#150
b0 T
b110 Q
b11000000000000000000000000000000 "
b11000000000000000000000000000000 .
b11000000000000000000000000000000 R
b1100 U
b10010100 +
1%
#151
0%
#152
b101 Q
b0 U
0S
b11011 T
0&
b110000 )
b10010110 +
1%
#153
0%
#154
b11101 T
b11011 U
b10011000 +
1%
#155
0%
#156
b10110 T
b11101 U
b10011010 +
1%
#157
0%
#158
b10000 T
b10110 U
b10011100 +
1%
#159
0%
#160
b10000 U
b1100 T
1S
1&
b110001 )
b10011110 +
1%
#161
0%
#162
b0 T
b100 Q
b11000000110000000000000000000000 "
b11000000110000000000000000000000 .
b11000000110000000000000000000000 R
b1100 U
b10100000 +
1%
#163
0%
#164
b11 Q
b0 U
b10100010 +
1%
#165
0%
#166
b10 Q
b10100100 +
1%
#167
0%
#168
b1 Q
b10100110 +
1%
#169
0%
#170
b0 Q
0S
b11011 T
0&
b110000 )
b10101000 +
1%
#171
0%
#172
b11101 T
b11011 U
b10101010 +
1%
#173
0%
#174
b11101 U
b10010 T
1&
b110001 )
b10101100 +
1%
#175
0%
#176
b10101 T
b10010 U
b10101110 +
1%
#177
0%
#178
b10101 U
b11110 T
0S
0&
b110000 )
b10110000 +
1%
#179
0%
#180
b110 T
1S
b11110 U
b10110010 +
1%
#181
0%
#182
b111 Q
b11000000110000000000000000000110 "
b11000000110000000000000000000110 .
b11000000110000000000000000000110 R
1!
1V
b110 U
b0 T
1S
1&
b110001 )
b10110100 +
1%
#183
0%
#184
b110 Q
b110000000000000000000110 "
b110000000000000000000110 .
b110000000000000000000110 R
0!
0V
b0 U
b1001 *
b10110110 +
1%
#185
0%
#186
b101 Q
b10111000 +
1%
#187
0%
#188
b100 Q
b110 "
b110 .
b110 R
0S
b11011 T
0&
b110000 )
b10111010 +
1%
#189
0%
#190
b11011 U
0S
b11000 T
1&
b110001 )
b10111100 +
1%
#191
0%
#192
1S
b11000 U
b1 T
0&
b110000 )
b10111110 +
1%
#193
0%
#194
b11 Q
b10000000000000110 "
b10000000000000110 .
b10000000000000110 R
b1 U
b0 T
1S
1&
b110001 )
b11000000 +
1%
#195
0%
#196
b10 Q
b0 U
b11000010 +
1%
#197
0%
#198
b1 Q
b11000100 +
1%
#199
0%
#200
b0 Q
b11000110 +
1%
#201
0%
#202
b111 Q
b10000000000000000 "
b10000000000000000 .
b10000000000000000 R
1!
1V
b11001000 +
1%
#203
0%
#204
b110 Q
0!
0V
b1010 *
b11001010 +
1%
#205
0%
#206
b101 Q
0S
b11011 T
0&
b110000 )
b11001100 +
1%
#207
0%
#208
b11101 T
b11011 U
b11001110 +
1%
#209
0%
#210
b11101 U
b10010 T
1&
b110001 )
b11010000 +
1%
#211
0%
#212
1S
b10010 U
b1101 T
0&
b110000 )
b11010010 +
1%
#213
0%
#214
0S
b11011 T
b100 Q
b110100010000000000000000 "
b110100010000000000000000 .
b110100010000000000000000 R
b1101 U
b11010100 +
1%
#215
0%
#216
b11011 U
0S
b11000 T
1&
b110001 )
b11010110 +
1%
#217
0%
#218
b11010 T
b11000 U
b11011000 +
1%
#219
0%
#220
b11010 U
b10 T
1S
0&
b110000 )
b11011010 +
1%
#221
0%
#222
0S
b11011 T
b11 Q
b110100100000000000000000 "
b110100100000000000000000 .
b110100100000000000000000 R
b10 U
b11011100 +
1%
#223
0%
#224
b11101 T
b11011 U
b11011110 +
1%
#225
0%
#226
b11101 U
b10010 T
1&
b110001 )
b11100000 +
1%
#227
0%
#228
1S
b10010 U
b1101 T
0&
b110000 )
b11100010 +
1%
#229
0%
#230
b10 Q
b110100101101000000000000 "
b110100101101000000000000 .
b110100101101000000000000 R
b1101 U
b0 T
1S
1&
b110001 )
b11100100 +
1%
#231
0%
#232
b1 Q
b0 U
0S
b11011 T
0&
b110000 )
b11100110 +
1%
#233
0%
#234
b11101 T
b11011 U
b11101000 +
1%
#235
0%
#236
b11101 U
b10010 T
1&
b110001 )
b11101010 +
1%
#237
0%
#238
b10101 T
b10010 U
b11101100 +
1%
#239
0%
#240
b1110 T
1S
b10101 U
b11101110 +
1%
#241
0%
#242
b0 Q
b110100101101000011100000 "
b110100101101000011100000 .
b110100101101000011100000 R
b1110 U
b11011 T
0S
0&
b110000 )
b11110000 +
1%
#243
0%
#244
b11011 U
0S
b11000 T
1&
b110001 )
b11110010 +
1%
#245
0%
#246
1S
b11000 U
b1 T
0&
b110000 )
b11110100 +
1%
#247
0%
#248
b111 Q
b110100101101000011100001 "
b110100101101000011100001 .
b110100101101000011100001 R
1!
1V
b1 U
b0 T
1S
1&
b110001 )
b11110110 +
1%
#249
0%
#250
b110 Q
0!
0V
b0 U
b1011 *
b11111000 +
1%
#251
0%
#252
b101 Q
0S
b11011 T
0&
b110000 )
b11111010 +
1%
#253
0%
#254
b11011 U
0S
b11000 T
1&
b110001 )
b11111100 +
1%
#255
0%
#256
b11010 T
b11000 U
b11111110 +
1%
#257
0%
#258
b11010 U
b10 T
1S
0&
b110000 )
b100000000 +
1%
#259
0%
#260
0S
b11011 T
b100 Q
b1000101101000011100001 "
b1000101101000011100001 .
b1000101101000011100001 R
b10 U
b100000010 +
1%
#261
0%
#262
b11101 T
b11011 U
b100000100 +
1%
#263
0%
#264
b10110 T
b11101 U
b100000110 +
1%
#265
0%
#266
b10000 T
b10110 U
b100001000 +
1%
#267
0%
#268
b10000 U
b1100 T
1S
1&
b110001 )
b100001010 +
1%
#269
0%
#270
b0 T
b11 Q
b1011001101000011100001 "
b1011001101000011100001 .
b1011001101000011100001 R
b1100 U
b100001100 +
1%
#271
0%
#272
b10 Q
b1011000000000011100001 "
b1011000000000011100001 .
b1011000000000011100001 R
b0 U
b100001110 +
1%
#273
0%
#274
b1 Q
0S
b11011 T
0&
b110000 )
b100010000 +
1%
#275
0%
#276
b11011 U
0S
b11000 T
1&
b110001 )
b100010010 +
1%
#277
0%
#278
b11010 T
b11000 U
b100010100 +
1%
#279
0%
#280
b11010 U
b10 T
1S
0&
b110000 )
b100010110 +
1%
#281
0%
#282
b0 Q
b1011000000000000100001 "
b1011000000000000100001 .
b1011000000000000100001 R
b10 U
b0 T
1S
1&
b110001 )
b100011000 +
1%
#283
0%
#284
b111 Q
b1011000000000000100000 "
b1011000000000000100000 .
b1011000000000000100000 R
1!
1V
b0 U
0S
b11011 T
0&
b110000 )
b100011010 +
1%
#285
0%
#286
b11101 T
0!
0V
b11011 U
b1100 *
b100011100 +
1%
#287
0%
#288
b11101 U
b10010 T
1&
b110001 )
b100011110 +
1%
#289
0%
#290
1S
b10010 U
b1101 T
0&
b110000 )
b100100000 +
1%
#291
0%
#292
b110 Q
b11010000001011000000000000100000 "
b11010000001011000000000000100000 .
b11010000001011000000000000100000 R
b1101 U
b0 T
1S
1&
b110001 )
b100100010 +
1%
#293
0%
#294
b101 Q
b0 U
b100100100 +
1%
#295
0%
#296
b100 Q
b11010000000011000000000000100000 "
b11010000000011000000000000100000 .
b11010000000011000000000000100000 R
b100100110 +
1%
#297
0%
#298
b11 Q
b11010000000000000000000000100000 "
b11010000000000000000000000100000 .
b11010000000000000000000000100000 R
0S
b11011 T
0&
b110000 )
b100101000 +
1%
#299
0%
#300
b11011 U
0S
b11000 T
1&
b110001 )
b100101010 +
1%
#301
0%
#302
1S
b11000 U
b1 T
0&
b110000 )
b100101100 +
1%
#303
0%
#304
b10 Q
b11010000000000000001000000100000 "
b11010000000000000001000000100000 .
b11010000000000000001000000100000 R
b1 U
b0 T
1S
1&
b110001 )
b100101110 +
1%
#305
0%
#306
b1 Q
b0 U
0S
b11011 T
0&
b110000 )
b100110000 +
1%
#307
0%
#308
b11011 U
0S
b11000 T
1&
b110001 )
b100110010 +
1%
#309
0%
#310
b11010 T
b11000 U
b100110100 +
1%
#311
0%
#312
b11010 U
b10 T
1S
0&
b110000 )
b100110110 +
1%
#313
0%
#314
b0 Q
b10 U
b0 T
1S
1&
b110001 )
b100111000 +
1%
#315
0%
#316
b111 Q
1!
1V
b0 U
b100111010 +
1%
#317
0%
#318
b110 Q
b1000000100000 "
b1000000100000 .
b1000000100000 R
0!
0V
b1101 *
b100111100 +
1%
#319
0%
#320
b101 Q
b100111110 +
1%
#321
0%
#322
b100 Q
b101000000 +
1%
#323
0%
#324
b11 Q
b101000010 +
1%
#325
0%
#326
b10 Q
b100000 "
b100000 .
b100000 R
b101000100 +
1%
#327
0%
#328
b1 Q
b101000110 +
1%
#329
0%
#330
b0 Q
b0 "
b0 .
b0 R
b101001000 +
1%
#331
0%
#332
b111 Q
1!
1V
0S
b11011 T
0&
b110000 )
b101001010 +
1%
#333
0%
#334
0!
0V
b11011 U
0S
b11000 T
b1110 *
1&
b110001 )
b101001100 +
1%
#335
0%
#336
1S
b11000 U
b1 T
0&
b110000 )
b101001110 +
1%
#337
0%
#338
b110 Q
b10000000000000000000000000000 "
b10000000000000000000000000000 .
b10000000000000000000000000000 R
b1 U
b0 T
1S
1&
b110001 )
b101010000 +
1%
#339
0%
#340
b101 Q
b0 U
b101010010 +
1%
#341
0%
#342
b100 Q
0S
b11011 T
0&
b110000 )
b101010100 +
1%
#343
0%
#344
b11011 U
0S
b11000 T
1&
b110001 )
b101010110 +
1%
#345
0%
#346
b11010 T
b11000 U
b101011000 +
1%
#347
0%
#348
b11010 U
b10 T
1S
0&
b110000 )
b101011010 +
1%
#349
0%
#350
b11 Q
b10000000000100000000000000000 "
b10000000000100000000000000000 .
b10000000000100000000000000000 R
b10 U
b0 T
1S
1&
b110001 )
b101011100 +
1%
#351
0%
#352
b10 Q
b0 U
b101011110 +
1%
#353
0%
#354
b1 Q
b101100000 +
1%
#355
0%
#356
b0 Q
0S
b11011 T
0&
b110000 )
b101100010 +
1%
#357
0%
#358
b11101 T
b11011 U
b101100100 +
1%
#359
0%
#360
b11101 U
b10010 T
1&
b110001 )
b101100110 +
1%
#361
0%
#362
1S
b10010 U
b1101 T
0&
b110000 )
b101101000 +
1%
#363
0%
#364
b111 Q
b10000000000100000000000001101 "
b10000000000100000000000001101 .
b10000000000100000000000001101 R
1!
1V
b1101 U
b0 T
1S
1&
b110001 )
b101101010 +
1%
#365
0%
#366
b110 Q
b100000000000001101 "
b100000000000001101 .
b100000000000001101 R
0!
0V
b0 U
b1111 *
b101101100 +
1%
#367
0%
#368
b101 Q
0S
b11011 T
0&
b110000 )
b101101110 +
1%
#369
0%
#370
b11011 U
0S
b11000 T
1&
b110001 )
b101110000 +
1%
#371
0%
#372
b11010 T
b11000 U
b101110010 +
1%
#373
0%
#374
b11010 U
b10 T
1S
0&
b110000 )
b101110100 +
1%
#375
0%
#376
0S
b11011 T
b100 Q
b1000100000000000001101 "
b1000100000000000001101 .
b1000100000000000001101 R
b10 U
b101110110 +
1%
#377
0%
#378
b11101 T
b11011 U
b101111000 +
1%
#379
0%
#380
b11101 U
b10010 T
1&
b110001 )
b101111010 +
1%
#381
0%
#382
b10101 T
b10010 U
b101111100 +
1%
#383
0%
#384
b1110 T
1S
b10101 U
b101111110 +
1%
#385
0%
#386
b11 Q
b1011100000000000001101 "
b1011100000000000001101 .
b1011100000000000001101 R
b1110 U
b11011 T
0S
0&
b110000 )
b110000000 +
1%
#387
0%
#388
b11011 U
0S
b11000 T
1&
b110001 )
b110000010 +
1%
#389
0%
#390
1S
b11000 U
b1 T
0&
b110000 )
b110000100 +
1%
#391
0%
#392
b10 Q
b1011100001000000001101 "
b1011100001000000001101 .
b1011100001000000001101 R
b1 U
b0 T
1S
1&
b110001 )
b110000110 +
1%
#393
0%
#394
b1 Q
b0 U
b110001000 +
1%
#395
0%
#396
b0 Q
b110001010 +
1%
#397
0%
#398
b111 Q
b1011100001000000000000 "
b1011100001000000000000 .
b1011100001000000000000 R
1!
1V
b110001100 +
1%
#399
0%
#400
b110 Q
0!
0V
b10000 *
b110001110 +
1%
#401
0%
#402
b101 Q
b110010000 +
1%
#403
0%
#404
b100 Q
b11100001000000000000 "
b11100001000000000000 .
b11100001000000000000 R
b110010010 +
1%
#405
0%
#406
b11 Q
b1000000000000 "
b1000000000000 .
b1000000000000 R
b110010100 +
1%
#407
0%
#408
b10 Q
b0 "
b0 .
b0 R
b110010110 +
1%
#409
0%
#410
b1 Q
b110011000 +
1%
#411
0%
#412
b0 Q
0S
b11011 T
0&
b110000 )
b110011010 +
1%
#413
0%
#414
b11011 U
0S
b11000 T
1&
b110001 )
b110011100 +
1%
#415
0%
#416
1S
b11000 U
b1 T
0&
b110000 )
b110011110 +
1%
#417
0%
#418
b111 Q
b1 "
b1 .
b1 R
1!
1V
b1 U
b0 T
1S
1&
b110001 )
b110100000 +
1%
#419
0%
#420
b110 Q
0!
0V
b0 U
b10001 *
b110100010 +
1%
#421
0%
#422
b101 Q
b110100100 +
1%
#423
0%
